__init__.py
arm_segmentation/__init__.py
arm_segmentation/predictor.py
arm_segmentation/train.py
arm_segmentation/visualize_validation.py
arm_segmentation/viz.py
detection/__init__.py
detection/coco_utils.py
detection/engine.py
detection/transforms.py
detection/utils.py
arm_segmentation-0.0.8.dist-info/METADATA
arm_segmentation-0.0.8.dist-info/WHEEL
arm_segmentation-0.0.8.dist-info/top_level.txt
arm_segmentation-0.0.8.dist-info/RECORD
