Metadata-Version: 2.1
Name: arm-segmentation
Version: 0.0.8
Summary: Training and inference of instance segmentation
Author-email: Peter Mitrano <pmitrano@umich.edu>
Maintainer-email: Peter Mitrano <pmitrano@umich.edu>
Requires-Python: >=3.6
Requires-Dist: torch
Requires-Dist: torchvision
Requires-Dist: pycocotools
Requires-Dist: numpy
Requires-Dist: matplotlib
Provides-Extra: test
Requires-Dist: pytest ; extra == 'test'
